{
 "id": "04d7ef3f-861f-40af-aff3-1bf03e851862",
 "title": {
  "en": "Zoku Shin Wild 7"
 },
 "contentRating": "suggestive",
 "matches": [
  {
   "id": "819742bb-21a0-445e-9920-5f8dec6fcf16",
   "title": {
    "en": "The Small Tatami of the Great Plain"
   },
   "contentRating": "suggestive",
   "score": 0.2937036
  },
  {
   "id": "8488bb32-5b67-4eb2-a19d-befcc446a488",
   "title": {
    "en": "Unknown"
   },
   "contentRating": "suggestive",
   "score": 0.22944199,
   "languages": [
    "en"
   ]
  },
  {
   "id": "b3683a72-dedf-4981-ad2f-d8d1e597718d",
   "title": {
    "en": "Golgo 13"
   },
   "contentRating": "suggestive",
   "score": 0.22828512,
   "languages": [
    "en",
    "ru",
    "fr"
   ]
  },
  {
   "id": "c4d0c41b-5f1a-4f72-909c-c4d67278bf78",
   "title": {
    "en": "Showa Phantoms - Those Unforgettable Guys"
   },
   "contentRating": "suggestive",
   "score": 0.2269582
  },
  {
   "id": "5eb514bc-bb37-4f37-a2e9-def530b08c29",
   "title": {
    "en": "Gift±"
   },
   "contentRating": "suggestive",
   "score": 0.22186889,
   "languages": [
    "ru",
    "es-la"
   ]
  },
  {
   "id": "50ced036-edd9-43e6-aff9-14a691071456",
   "title": {
    "en": "Kamen Rider Kuuga"
   },
   "contentRating": "suggestive",
   "score": 0.22151163,
   "languages": [
    "es",
    "en",
    "pt-br",
    "id"
   ]
  },
  {
   "id": "50c60dac-0a38-4da9-92f6-f544cf7c87af",
   "title": {
    "en": "Legend of the Holy Common Man"
   },
   "contentRating": "suggestive",
   "score": 0.20991726
  },
  {
   "id": "4e6c7ed7-2111-4a3b-b34c-fbf07b1884c4",
   "title": {
    "en": "Gangsta"
   },
   "contentRating": "suggestive",
   "score": 0.20858364,
   "languages": [
    "ru",
    "id",
    "tr",
    "pt-br",
    "en",
    "pl",
    "it"
   ]
  },
  {
   "id": "2c005595-d633-4bc6-9237-afcf79a7985a",
   "title": {
    "en": "Mobile Suit Gundam Rust Horizon"
   },
   "contentRating": "suggestive",
   "score": 0.20411375
  },
  {
   "id": "e660da42-375c-4fca-80f1-1afbe5342b8f",
   "title": {
    "en": "Fool Night"
   },
   "contentRating": "suggestive",
   "score": 0.20336902,
   "languages": [
    "pt-br",
    "ru",
    "en",
    "id",
    "uk"
   ]
  },
  {
   "id": "a0c79b5e-0d92-4bad-8dd6-734e60e94ee9",
   "title": {
    "en": "Every Minute Ends"
   },
   "contentRating": "suggestive",
   "score": 0.20234534,
   "languages": [
    "fr",
    "en",
    "id"
   ]
  },
  {
   "id": "6da0b34b-db19-491a-b85c-6e31e0986f15",
   "title": {
    "en": "Black Lagoon"
   },
   "contentRating": "suggestive",
   "score": 0.20151092,
   "languages": [
    "it",
    "ru",
    "pt-br",
    "en",
    "es",
    "fr"
   ]
  }
 ],
 "updatedAt": "2023-01-13T08:47:56+00:00"
}