{
 "id": "13c56f24-9ce5-42ee-a0ad-8797d82881c5",
 "title": {
  "en": "A Midsummer Night's Dream"
 },
 "contentRating": "safe",
 "matches": [
  {
   "id": "56219b48-3203-416d-9ea8-acf5352f55a3",
   "title": {
    "en": "Yuki wa Jigoku ni Ochiru no Ka"
   },
   "contentRating": "safe",
   "score": 0.4357511,
   "languages": [
    "en"
   ]
  },
  {
   "id": "4b039a48-c4c9-4e19-90ca-ced5779e5810",
   "title": {
    "en": "Akai Ito"
   },
   "contentRating": "safe",
   "score": 0.40493655,
   "languages": [
    "en",
    "pl",
    "hu"
   ]
  },
  {
   "id": "85b11eaf-6de0-48d2-8d66-f39ab0852ac4",
   "title": {
    "en": "Red Girl"
   },
   "contentRating": "safe",
   "score": 0.4000316,
   "languages": [
    "en"
   ]
  },
  {
   "id": "c34a27d5-a670-4bb1-b805-3e78bc2f7f39",
   "title": {
    "en": "Sasagu Omoi wa Hana Meguri"
   },
   "contentRating": "safe",
   "score": 0.39981887,
   "languages": [
    "en"
   ]
  },
  {
   "id": "50acd4ef-7415-4102-9482-a3fb698b9a52",
   "title": {
    "en": "Strawberry Holiday"
   },
   "contentRating": "safe",
   "score": 0.39728287,
   "languages": [
    "en"
   ]
  },
  {
   "id": "67813769-3476-46fe-9be5-3fe5d3479d3d",
   "title": {
    "en": "Haru Machi Sakura no Mau Koro ni"
   },
   "contentRating": "safe",
   "score": 0.39600566,
   "languages": [
    "en"
   ]
  },
  {
   "id": "057cbb2f-2c25-4f86-a4b0-66c8b0c90892",
   "title": {
    "en": "Heartland no Juunin"
   },
   "contentRating": "safe",
   "score": 0.39510888,
   "languages": [
    "en"
   ]
  },
  {
   "id": "8728e845-9be8-4b9c-b59c-d09bbfd754de",
   "title": {
    "en": "Bunbetsu to Takan"
   },
   "contentRating": "safe",
   "score": 0.3767105,
   "languages": [
    "en"
   ]
  },
  {
   "id": "5a80f268-0306-4593-965e-d0880d11ec0d",
   "title": {
    "en": "Hotarubi no Mori e"
   },
   "contentRating": "safe",
   "score": 0.36910367,
   "languages": [
    "es",
    "en",
    "it",
    "tr"
   ]
  },
  {
   "id": "defe9d28-37f6-4e63-8616-862adb8315d5",
   "title": {
    "en": "Lonesome Eden"
   },
   "contentRating": "safe",
   "score": 0.36896917,
   "languages": [
    "it",
    "en"
   ]
  },
  {
   "id": "3935f730-ecbd-4c65-b537-e20aa6a4125d",
   "title": {
    "en": "Hatsukoi Harinezumi"
   },
   "contentRating": "safe",
   "score": 0.36511785,
   "languages": [
    "en"
   ]
  },
  {
   "id": "722a8e72-bc43-4a5c-b5f6-96413bd3a7b4",
   "title": {
    "en": "Good Person"
   },
   "contentRating": "safe",
   "score": 0.3630355,
   "languages": [
    "en"
   ]
  }
 ],
 "updatedAt": "2022-01-03T05:18:20+00:00"
}