{
 "id": "14ee6a1f-fa8f-4b32-82e5-6648a2825c34",
 "title": {
  "en": "Ponkotsu ga Tensei Shitara Zongai Saikyou"
 },
 "contentRating": "suggestive",
 "matches": [
  {
   "id": "b6f8c7b9-eeae-4698-a0e7-05474f56b644",
   "title": {
    "en": "Douyara Watashi no Karada wa Kanzen Muteki no You Desu ne"
   },
   "contentRating": "suggestive",
   "score": 0.31096983,
   "languages": [
    "id",
    "en",
    "ru",
    "pt-br"
   ]
  },
  {
   "id": "975f3334-8395-4393-84a2-50fcaccbcdc0",
   "title": {
    "en": "Fantasy Bishoujo Juniku Ojisan to"
   },
   "contentRating": "suggestive",
   "score": 0.2756281,
   "languages": [
    "en",
    "pt-br",
    "fr",
    "it"
   ]
  },
  {
   "id": "ffe69cc2-3f9e-4eab-a7f7-c963cea9ec25",
   "title": {
    "en": "Hitoribocchi no Isekai Kouryaku"
   },
   "contentRating": "suggestive",
   "score": 0.27309445,
   "languages": [
    "es-la",
    "pt-br",
    "ru",
    "en",
    "vi",
    "pl",
    "id"
   ]
  },
  {
   "id": "abd0bc20-063a-45a0-91b2-8b7049701d4a",
   "title": {
    "en": "Saikyou Onmyouji no Isekai Tensei-ki ~Geboku no Youkai-domo ni Kurabete Monster ga Yowasugiru n da ga~"
   },
   "contentRating": "suggestive",
   "score": 0.2721697,
   "languages": [
    "fr",
    "en",
    "es-la",
    "pt-br",
    "ru"
   ]
  },
  {
   "id": "1ee404fd-2774-4030-929d-405451f885b7",
   "title": {
    "en": "Tensei Shita Moto Dorei, Saikyou no Kizoku ni Natte Toshiue no Musume to Sekai Saikyou wo Mezashimas"
   },
   "contentRating": "suggestive",
   "score": 0.2676879,
   "languages": [
    "en"
   ]
  },
  {
   "id": "6b06fe1e-ff99-4c8d-be0b-5ad2a4df7603",
   "title": {
    "en": "Kajiya de Hajimeru Isekai Slow Life"
   },
   "contentRating": "suggestive",
   "score": 0.26497757,
   "languages": [
    "ru",
    "th",
    "it",
    "fr",
    "en",
    "id"
   ]
  },
  {
   "id": "06aa99db-35ef-4da9-8f03-883f02c7837b",
   "title": {
    "en": "I Came to Another World as a Jack of All Trades and a Master of None to Journey While Relying on Quickness"
   },
   "contentRating": "suggestive",
   "score": 0.25892407,
   "languages": [
    "id",
    "en",
    "pt-br"
   ]
  },
  {
   "id": "08a5070d-f9ff-4f83-ace7-951952bceb66",
   "title": {
    "en": "Gun-Ota ga Mahou Sekai ni Tensei shitara, Gendai Heiki de Guntai Harem wo Tsukucchaimashita!?"
   },
   "contentRating": "suggestive",
   "score": 0.25610226,
   "languages": [
    "en",
    "es-la",
    "fr",
    "pt-br",
    "ru",
    "es"
   ]
  },
  {
   "id": "c7311cec-9b0f-42f3-8afe-a06cb5b70229",
   "title": {
    "en": "Isekai de Skill wo Kaitai Shitara Cheat na Yome ga Zoushoku Shimashita: Gainen Kousa no Structure"
   },
   "contentRating": "suggestive",
   "score": 0.2553623,
   "languages": [
    "en",
    "pt-br",
    "ru",
    "es-la",
    "id",
    "fr",
    "it"
   ]
  },
  {
   "id": "248525ed-ad1c-4ddc-a834-5d6ce66a3ad2",
   "title": {
    "en": "Arifureta Shokugyou de Sekai Saikyou"
   },
   "contentRating": "suggestive",
   "score": 0.25469035,
   "languages": [
    "it",
    "es-la",
    "ru",
    "pl",
    "pt-br",
    "en",
    "fr",
    "hu",
    "id",
    "tr",
    "vi",
    "fa",
    "de"
   ]
  },
  {
   "id": "397bd865-58d0-4445-be1c-ea6c20c5c9b0",
   "title": {
    "en": "Zettai ni Yatte wa Ikenai Isekai Shoukan"
   },
   "contentRating": "suggestive",
   "score": 0.24958156,
   "languages": [
    "es-la",
    "en",
    "id",
    "es"
   ]
  },
  {
   "id": "0dac60e0-1358-44dd-88cf-927a5fcff348",
   "title": {
    "en": "Level 1 Dakedo Unique Skill de Saikyou desu"
   },
   "contentRating": "suggestive",
   "score": 0.24514247,
   "languages": [
    "en",
    "fr",
    "id",
    "pt-br"
   ]
  },
  {
   "id": "eb5a4a48-61c3-4f0a-a2c3-1c284b4752ce",
   "title": {
    "en": "Rettou Gan no Tensei Majutsushi ~ Shiitagerareta Moto Yuusha wa Mirai no Sekai o Yoyuu de Ikinuku ~"
   },
   "contentRating": "suggestive",
   "score": 0.2421281,
   "languages": [
    "en",
    "ru",
    "id",
    "pt-br",
    "fr",
    "it"
   ]
  },
  {
   "id": "fe840e8f-1267-4611-869b-9ab290dc205b",
   "title": {
    "en": "The Legendary Weapon Became My Bride When I Overwhelmed the Production Job"
   },
   "contentRating": "suggestive",
   "score": 0.23939762,
   "languages": [
    "en",
    "pt-br"
   ]
  },
  {
   "id": "9859dda5-d45d-406a-ab95-02e8b7a4b02b",
   "title": {
    "en": "Arifureta Gakuen de Sekai Saikyou"
   },
   "contentRating": "suggestive",
   "score": 0.23916925,
   "languages": [
    "en",
    "ru",
    "id"
   ]
  },
  {
   "id": "d7d6829b-ceab-4346-a033-22387aeff297",
   "title": {
    "en": "Isekai Shoukan wa Nidome Desu"
   },
   "contentRating": "suggestive",
   "score": 0.23765847,
   "languages": [
    "en",
    "fr",
    "es-la",
    "ru",
    "pt-br",
    "es"
   ]
  }
 ],
 "updatedAt": "2023-07-11T06:16:39+00:00"
}