{
 "id": "5048be88-e228-441d-ad01-dc07e76f1c82",
 "title": {
  "en": "Senran Kagura - Ikaruga Inran Zoushi (Doujinshi)"
 },
 "contentRating": "pornographic",
 "matches": [
  {
   "id": "2a9f3cdf-6201-41cf-b5f0-5fd039d2e031",
   "title": {
    "en": "Oshioki Sweetie - Sweet Time (Doujinshi)"
   },
   "contentRating": "pornographic",
   "score": 0.44236442,
   "languages": [
    "en"
   ]
  },
  {
   "id": "bc5d4190-f9e2-4a6d-8d6c-a42b12d714c6",
   "title": {
    "en": "Sokuhame Dekichau JK Miya-chan no Gakkou"
   },
   "contentRating": "pornographic",
   "score": 0.43423644,
   "languages": [
    "en"
   ]
  },
  {
   "id": "f9643a3b-eb01-487f-b968-5ee68f606c93",
   "title": {
    "en": "Gundam Build Fighters Try - C9-15 Fumina-senpai to Mob Onii-chan (Doujinshi)"
   },
   "contentRating": "pornographic",
   "score": 0.4230998,
   "languages": [
    "en"
   ]
  },
  {
   "id": "a2bbee03-fd47-438e-b127-171486035645",
   "title": {
    "en": "Azur Lane - Do you like sister ships in uniform?"
   },
   "contentRating": "pornographic",
   "score": 0.41030443,
   "languages": [
    "en"
   ]
  },
  {
   "id": "94b7f175-e3bd-444e-bc87-fb8470adca58",
   "title": {
    "en": "Azur Lane - Zurifunction (Doujinshi)"
   },
   "contentRating": "pornographic",
   "score": 0.40829974,
   "languages": [
    "en"
   ]
  },
  {
   "id": "f690bf19-38de-46cb-a5ef-cc9500c9e7fa",
   "title": {
    "en": "Kaguya-sama wa Kokurasetai - Fujiwara-shoki wa Kotowaritai (Doujinshi)"
   },
   "contentRating": "pornographic",
   "score": 0.40803662,
   "languages": [
    "en"
   ]
  },
  {
   "id": "5c64ae5d-36d8-4426-9159-d74e4b98c3d6",
   "title": {
    "en": "Amagami - Kamen Kyousei Event (Doujinshi)"
   },
   "contentRating": "pornographic",
   "score": 0.4034213,
   "languages": [
    "en"
   ]
  },
  {
   "id": "73d93a7d-7d10-403f-a5fd-1086416135af",
   "title": {
    "en": "THE IDOLM@STER CINDERELLA GIRLS - The Dark Side of the Moon (Doujinshi)"
   },
   "contentRating": "pornographic",
   "score": 0.4026374,
   "languages": [
    "en"
   ]
  },
  {
   "id": "984e393f-516d-4468-9b24-b2cbe87e0388",
   "title": {
    "en": "Love Live! - Shocking! Love Arrow (Doujinshi)"
   },
   "contentRating": "pornographic",
   "score": 0.39968327,
   "languages": [
    "en"
   ]
  },
  {
   "id": "c71f1a9b-4a8e-421d-83cf-e6b7e2eaef49",
   "title": {
    "en": "Love Live! Nijigasaki High School Idol Club - Karin to Icha Love Ecchi (Doujinshi)"
   },
   "contentRating": "pornographic",
   "score": 0.3996093,
   "languages": [
    "en"
   ]
  },
  {
   "id": "7fac55cd-9b37-47ef-85ae-c984e3131eeb",
   "title": {
    "en": "SSSS.Gridman - Namaashi Cardigan (Doujinshi)"
   },
   "contentRating": "pornographic",
   "score": 0.3993331,
   "languages": [
    "en"
   ]
  },
  {
   "id": "7dcc082f-d5b3-4738-bb86-501f0f381496",
   "title": {
    "en": "Hyouka - Oishii Amazake Recipe!! (Doujinshi)"
   },
   "contentRating": "pornographic",
   "score": 0.39594114,
   "languages": [
    "en"
   ]
  },
  {
   "id": "9fc76baa-725a-429a-991a-d4358db2cd98",
   "title": {
    "en": "Azur Lane - Kakin Shikikan, Fuku o Kau. (Doujinshi)"
   },
   "contentRating": "pornographic",
   "score": 0.39530653,
   "languages": [
    "en"
   ]
  },
  {
   "id": "5f380667-b097-474c-afb2-66f7403ff744",
   "title": {
    "en": "I'm yours."
   },
   "contentRating": "pornographic",
   "score": 0.39412853,
   "languages": [
    "en"
   ]
  },
  {
   "id": "5f22b18d-4759-4df6-a5e0-8d5ebd45bc13",
   "title": {
    "en": "Ore no Imouto ga Konna ni Kawaii Wake ga Nai - My Lovely Angel!? Ayase-tan (Doujinshi)"
   },
   "contentRating": "pornographic",
   "score": 0.39332628,
   "languages": [
    "en"
   ]
  },
  {
   "id": "9cb8d0ca-bad5-41e8-8dc4-8aaced0bf3ca",
   "title": {
    "en": "THE iDOLM@STER - Itadakimasu Anata-sama (Doujinshi)"
   },
   "contentRating": "pornographic",
   "score": 0.3930508,
   "languages": [
    "en"
   ]
  }
 ],
 "updatedAt": "2025-01-06T00:13:48+00:00"
}