{
 "id": "5b516ebf-f5b1-4791-87f3-c91709d7fe4b",
 "title": {
  "en": "Koitsu no Nioi de Kyousei Hatsujou"
 },
 "contentRating": "erotica",
 "matches": [
  {
   "id": "b72f3a52-19df-4068-9094-94aaeb546dfa",
   "title": {
    "en": "Ijiwaru Joukyuu Kokumin wa Jouhinna Yajuu ~Gokujou SEX ni Gakeppuchi Hoikushi wa Asamade Torokeru~"
   },
   "contentRating": "erotica",
   "score": 0.36355105,
   "languages": [
    "en"
   ]
  },
  {
   "id": "48d6058e-27d1-430e-9b84-019349416f2c",
   "title": {
    "en": "The Bud and the Florist - First Time I Wet Myself With Your Fingers..."
   },
   "contentRating": "erotica",
   "score": 0.3576682,
   "languages": [
    "en"
   ]
  },
  {
   "id": "64956f75-1bde-47d9-8f88-bf1a6526fe19",
   "title": {
    "en": "Boku shika Shiranai Kimi no Naka."
   },
   "contentRating": "erotica",
   "score": 0.35297695,
   "languages": [
    "en"
   ]
  },
  {
   "id": "d7fb6850-a2e8-47ea-bf5b-f452c91eee90",
   "title": {
    "en": "The Dinner with the Dormant Aphrodisiac Trap"
   },
   "contentRating": "erotica",
   "score": 0.35296774,
   "languages": [
    "en"
   ]
  },
  {
   "id": "c37373e6-4730-4aa3-a57e-de6414a4e1a4",
   "title": {
    "en": "Hajime Kara Suki Nanyaro? Kiryu Kairi Niwa Revenge ga Kakanai!"
   },
   "contentRating": "erotica",
   "score": 0.35103825,
   "languages": [
    "en"
   ]
  },
  {
   "id": "ab90c316-6e54-4d14-80c9-0773043b7998",
   "title": {
    "en": "Tada no Renai Nanka de Kikkonai"
   },
   "contentRating": "erotica",
   "score": 0.34903577,
   "languages": [
    "id",
    "en"
   ]
  },
  {
   "id": "17b84b3c-55a0-48fe-b87f-923727914e8b",
   "title": {
    "en": "Hatsujou Suru Unmei: Elite α no Risei ga Genkai"
   },
   "contentRating": "erotica",
   "score": 0.34715998,
   "languages": [
    "id",
    "en"
   ]
  },
  {
   "id": "644a51a5-971d-4b60-95c9-a92bb2a99bb7",
   "title": {
    "en": "He Doesn’t See Me"
   },
   "contentRating": "erotica",
   "score": 0.34476772,
   "languages": [
    "en"
   ]
  },
  {
   "id": "fc44dc1a-d7f0-46f5-b35c-c253f7baf83f",
   "title": {
    "en": "You’re the Only One Who Gets Me up ~Perfect Sexual Chemistry With a Childhood Friend"
   },
   "contentRating": "erotica",
   "score": 0.33922172,
   "languages": [
    "en"
   ]
  },
  {
   "id": "7fe7a5ca-201b-4985-8b72-023d55ee4548",
   "title": {
    "en": "I’ll Risk My Life to Love You - A Dangerous Boss Who Is Pretending to Be Innocent!?"
   },
   "contentRating": "erotica",
   "score": 0.3367187,
   "languages": [
    "en"
   ]
  },
  {
   "id": "e3d06a3f-6297-44f0-b17a-ef81207ac4b4",
   "title": {
    "en": "Zetsurin Yakuza no Gokujou Aibu Nogarerarenai Keiyaku Kekkon"
   },
   "contentRating": "erotica",
   "score": 0.33091995,
   "languages": [
    "en"
   ]
  },
  {
   "id": "ec2f9e28-2b9d-49ad-a6fd-6b7cf47fbd6a",
   "title": {
    "en": "Marriage and Sword"
   },
   "contentRating": "erotica",
   "score": 0.32997784,
   "languages": [
    "es-la",
    "pt-br",
    "pl",
    "en"
   ]
  },
  {
   "id": "e2c8b260-a46b-42bf-9c22-f0204e0970d1",
   "title": {
    "en": "Our Lust Is Out of Control"
   },
   "contentRating": "erotica",
   "score": 0.329423,
   "languages": [
    "en"
   ]
  },
  {
   "id": "27e5c136-8b26-4128-acb7-da3923673ae7",
   "title": {
    "en": "Lady-Killer Boss"
   },
   "contentRating": "erotica",
   "score": 0.32915068,
   "languages": [
    "en"
   ]
  },
  {
   "id": "aaf9964c-5031-4d3c-a8fe-ee6719dbc6f3",
   "title": {
    "en": "Stalker Shachou no Kareinaru Kyukon ~16-nenkan Suki Datta Nante Kiitemasen~"
   },
   "contentRating": "erotica",
   "score": 0.32880935,
   "languages": [
    "en"
   ]
  },
  {
   "id": "efdb794d-9c38-4b64-a33b-7d7d9f7b6cd4",
   "title": {
    "en": "My Carnivorous Young Boyfriend ~ He Puts It in Again When I’m Worn Out From Coming"
   },
   "contentRating": "erotica",
   "score": 0.327956,
   "languages": [
    "en"
   ]
  }
 ],
 "updatedAt": "2024-05-05T18:24:56+00:00"
}