{
 "id": "8f052ca9-973d-4770-a133-ed01e558cd1e",
 "title": {
  "en": "Upon the White Tiger"
 },
 "contentRating": "safe",
 "matches": [
  {
   "id": "3023884c-2691-4da6-ab9b-455c5511fa44",
   "title": {
    "en": "Her Highness Is Mighty"
   },
   "contentRating": "safe",
   "score": 0.45166752,
   "languages": [
    "en",
    "fr",
    "id"
   ]
  },
  {
   "id": "8d1b8d96-2052-499e-b78e-7f52921789e7",
   "title": {
    "en": "Possession"
   },
   "contentRating": "safe",
   "score": 0.4437109,
   "languages": [
    "fr",
    "pt-br",
    "en"
   ]
  },
  {
   "id": "6cb7a1b1-719b-4322-b659-2c2ca196229f",
   "title": {
    "en": "White Wheel of Fortune"
   },
   "contentRating": "safe",
   "score": 0.441522,
   "languages": [
    "fr",
    "en"
   ]
  },
  {
   "id": "0e2f825b-36a1-4542-bbc1-f82077ed2fe4",
   "title": {
    "en": "Rebirth of the Butterfly Girl"
   },
   "contentRating": "safe",
   "score": 0.41520074,
   "languages": [
    "en",
    "fr"
   ]
  },
  {
   "id": "749f2401-eee0-4ab5-aff3-1cef89b43711",
   "title": {
    "en": "I Saved the Cursed Duke"
   },
   "contentRating": "safe",
   "score": 0.4107919,
   "languages": [
    "id",
    "fr",
    "en",
    "ru"
   ]
  },
  {
   "id": "123639c6-d926-4dfe-8807-465ff029794e",
   "title": {
    "en": "Oh My God"
   },
   "contentRating": "safe",
   "score": 0.4107919,
   "languages": [
    "en",
    "fr"
   ]
  },
  {
   "id": "9044f339-82f3-4848-9997-34437d2b3348",
   "title": {
    "en": "7:30 Mobile Time"
   },
   "contentRating": "safe",
   "score": 0.4107919,
   "languages": [
    "fr",
    "en"
   ]
  },
  {
   "id": "0686d85b-2bb8-4884-90a8-130474cbc1dc",
   "title": {
    "en": "This Boy Got Me Falling Hard"
   },
   "contentRating": "safe",
   "score": 0.40249223,
   "languages": [
    "en",
    "fr"
   ]
  },
  {
   "id": "90758537-ae89-45c8-942f-b479f9c86bbe",
   "title": {
    "en": "Mommy Is Coming, Daddy Watch Out!"
   },
   "contentRating": "safe",
   "score": 0.40249223,
   "languages": [
    "fr",
    "en"
   ]
  },
  {
   "id": "23bdf39d-f52d-41c2-abb3-ff0b72a0ea4f",
   "title": {
    "en": "Heaven Guards"
   },
   "contentRating": "safe",
   "score": 0.39156368,
   "languages": [
    "fr",
    "en",
    "it"
   ]
  },
  {
   "id": "44bd2313-30a3-4bc5-840a-6c09ddac7f8d",
   "title": {
    "en": "You Are My Lovely Dragon King"
   },
   "contentRating": "safe",
   "score": 0.38300005,
   "languages": [
    "en",
    "fr"
   ]
  },
  {
   "id": "79eb00db-ca63-46e6-8041-36f808146aaa",
   "title": {
    "en": "Hello, Summer"
   },
   "contentRating": "safe",
   "score": 0.38197494,
   "languages": [
    "uk",
    "en",
    "fr"
   ]
  },
  {
   "id": "0a7f9cd8-890c-4543-8391-034e18a7d3c3",
   "title": {
    "en": "Bewitching Empress So Pampered by Her Tyrant"
   },
   "contentRating": "safe",
   "score": 0.38031942,
   "languages": [
    "en",
    "fr"
   ]
  },
  {
   "id": "4fa874aa-e7dc-4fb8-b0cd-c7fde3d7bf34",
   "title": {
    "en": "My Girlfriend Is a Dragon"
   },
   "contentRating": "safe",
   "score": 0.38031942,
   "languages": [
    "en",
    "fr"
   ]
  },
  {
   "id": "15588d53-d6e9-4c07-813f-5a4c65e51c0a",
   "title": {
    "en": "Falling in the Night with You"
   },
   "contentRating": "safe",
   "score": 0.38031942,
   "languages": [
    "en",
    "fr"
   ]
  },
  {
   "id": "bd7b45eb-1458-4804-a18e-1b9a244585f9",
   "title": {
    "en": "Magickology"
   },
   "contentRating": "safe",
   "score": 0.38031942,
   "languages": [
    "pt-br",
    "en",
    "fr"
   ]
  },
  {
   "id": "c64d02b3-2a65-4ae2-a3ca-d0e33062a463",
   "title": {
    "en": "By the Way, Dragon Mistress!"
   },
   "contentRating": "safe",
   "score": 0.38031942,
   "languages": [
    "en",
    "pt-br",
    "tr",
    "fr"
   ]
  },
  {
   "id": "a3ba9898-06cd-443c-915e-96e39669c73e",
   "title": {
    "en": "I'm Stanning the Prince"
   },
   "contentRating": "safe",
   "score": 0.38031942,
   "languages": [
    "es",
    "fr",
    "pt-br",
    "vi",
    "es-la",
    "tr",
    "en"
   ]
  },
  {
   "id": "247bd517-846e-41cb-b6ec-f368e9272d7c",
   "title": {
    "en": "Monster Duke's Daughter"
   },
   "contentRating": "safe",
   "score": 0.38031942,
   "languages": [
    "pt-br",
    "fr",
    "vi",
    "ru",
    "tr",
    "en"
   ]
  },
  {
   "id": "82cf0018-d918-46e6-9a61-9893d97b09ac",
   "title": {
    "en": "Stay Awake All Night"
   },
   "contentRating": "safe",
   "score": 0.38031942,
   "languages": [
    "en",
    "es",
    "fr",
    "tr",
    "id"
   ]
  },
  {
   "id": "9486360d-27aa-4fa1-b4a5-e47590bb2b83",
   "title": {
    "en": "Beyond The Manhwa"
   },
   "contentRating": "safe",
   "score": 0.38031942,
   "languages": [
    "en",
    "tr",
    "pt-br",
    "fr"
   ]
  },
  {
   "id": "66d121d8-3790-4468-ab74-343042ff1176",
   "title": {
    "en": "The 7th of July"
   },
   "contentRating": "safe",
   "score": 0.38031942,
   "languages": [
    "it",
    "en",
    "fr"
   ]
  },
  {
   "id": "881d3673-f101-4848-a56d-f2dd08a3383d",
   "title": {
    "en": "You Are My Destiny"
   },
   "contentRating": "safe",
   "score": 0.38031942,
   "languages": [
    "fr",
    "en"
   ]
  },
  {
   "id": "2e2743c1-e27f-4056-9faa-5ab65f1fe4eb",
   "title": {
    "en": "Unbending Flower"
   },
   "contentRating": "safe",
   "score": 0.38031942,
   "languages": [
    "fr",
    "id",
    "en",
    "pt-br"
   ]
  },
  {
   "id": "4ea47849-e06a-4dd8-921c-3330487454e1",
   "title": {
    "en": "Blinded by the Setting Sun"
   },
   "contentRating": "safe",
   "score": 0.38031942,
   "languages": [
    "en",
    "vi",
    "th",
    "fr"
   ]
  }
 ],
 "updatedAt": "2021-07-12T02:34:09+00:00"
}