{
 "id": "8fb61af8-534b-475b-a3f4-eec55c9d36f8",
 "title": {
  "en": "The Day Before"
 },
 "contentRating": "safe",
 "matches": [
  {
   "id": "1aaf8a01-72d5-4e2f-860b-ceb3c16040ec",
   "title": {
    "en": "Douse Buchou Wa"
   },
   "contentRating": "safe",
   "score": 0.26103282,
   "languages": [
    "en",
    "fr"
   ]
  },
  {
   "id": "1aa29670-ce7e-4dc4-b032-fa39e19dd241",
   "title": {
    "en": "Old-fashioned Cupcake"
   },
   "contentRating": "safe",
   "score": 0.25916255,
   "languages": [
    "en"
   ]
  },
  {
   "id": "e8d56d8a-241f-43b0-96e1-eb1106a44c99",
   "title": {
    "en": "Taikakusa"
   },
   "contentRating": "safe",
   "score": 0.2587061,
   "languages": [
    "en"
   ]
  },
  {
   "id": "6094aab5-b9ea-4b92-9885-1128a069a562",
   "title": {
    "en": "Satsubatsu Couple no Hanashi"
   },
   "contentRating": "safe",
   "score": 0.25658494,
   "languages": [
    "en",
    "fr",
    "es-la",
    "id"
   ]
  },
  {
   "id": "cd8b60d2-31af-4b82-9ef9-ce5c0785fa15",
   "title": {
    "en": "Ikeoji Monster to Zettai Reido Danshi"
   },
   "contentRating": "safe",
   "score": 0.25075945,
   "languages": [
    "en"
   ]
  },
  {
   "id": "4ffebdc2-51d3-445c-af11-ab49e01c3f48",
   "title": {
    "en": "Kachou Baka Ichidachi"
   },
   "contentRating": "safe",
   "score": 0.25040165,
   "languages": [
    "en"
   ]
  },
  {
   "id": "0550851a-961b-4b34-9684-4b2901e62079",
   "title": {
    "en": "Moto Azadarake no Kanojo ga Shinpai de"
   },
   "contentRating": "safe",
   "score": 0.24983342,
   "languages": [
    "pt-br",
    "id",
    "es-la",
    "en",
    "ru",
    "pl",
    "tr",
    "vi"
   ]
  },
  {
   "id": "061dfe00-45bb-4cd8-86fc-73bc5d749791",
   "title": {
    "en": "Daily Life of a Couple in Which the Boyfriend Became a Girl One Day"
   },
   "contentRating": "safe",
   "score": 0.24906911,
   "languages": [
    "id",
    "en",
    "vi"
   ]
  },
  {
   "id": "7aa9f32a-4934-44b6-9557-73c4089c969b",
   "title": {
    "en": "Yukinoshita-san and Her Manager"
   },
   "contentRating": "safe",
   "score": 0.24244238,
   "languages": [
    "en"
   ]
  },
  {
   "id": "623e8602-ffa4-4538-86fc-5e776fdf5831",
   "title": {
    "en": "Senpai to Kouhai Nomi"
   },
   "contentRating": "safe",
   "score": 0.24244238,
   "languages": [
    "en",
    "vi",
    "fr",
    "es-la"
   ]
  },
  {
   "id": "75160503-afb6-4a86-ba86-206a2d967a82",
   "title": {
    "en": "2 Centimeter Gossip"
   },
   "contentRating": "safe",
   "score": 0.24014586,
   "languages": [
    "en"
   ]
  },
  {
   "id": "af0e821d-bf0f-4f56-9a7b-a7b9074c1906",
   "title": {
    "en": "Aru Roufuufu no Nichijou"
   },
   "contentRating": "safe",
   "score": 0.2362182,
   "languages": [
    "en",
    "es-la"
   ]
  },
  {
   "id": "e14cc122-9b0d-4a62-ae99-a289bde5d4e0",
   "title": {
    "en": "Kare to Tsukiau 10 no Merit"
   },
   "contentRating": "safe",
   "score": 0.23253196,
   "languages": [
    "en"
   ]
  },
  {
   "id": "9036a7e6-690d-4ba9-ab57-65ee12185a32",
   "title": {
    "en": "Mitsuya Sensei no Keikakuteki na Edzuke"
   },
   "contentRating": "safe",
   "score": 0.23180202,
   "languages": [
    "en",
    "pt-br"
   ]
  },
  {
   "id": "3597f04d-eab8-4311-93aa-fd055e168e2c",
   "title": {
    "en": "Himitsu no Hodaka-kun wa Amai Nioi ga Suru"
   },
   "contentRating": "safe",
   "score": 0.23180202,
   "languages": [
    "en"
   ]
  },
  {
   "id": "b90b4118-4270-49d0-8787-cffb91a1290f",
   "title": {
    "en": "Mitasu No Wa Kuufuku Dake Desuka?"
   },
   "contentRating": "safe",
   "score": 0.23180202,
   "languages": [
    "en"
   ]
  }
 ],
 "updatedAt": "2024-04-29T18:25:35+00:00"
}