{
 "id": "9823a801-5597-4c56-a627-ae14f49ec28b",
 "title": {
  "en": "BanG Dream! - Hatarakikata Kaikaku (Doujinshi)"
 },
 "contentRating": "pornographic",
 "matches": [
  {
   "id": "1f764d8f-d6e9-400e-95a5-3f12e90206bd",
   "title": {
    "en": "BanG Dream! - Route Episode in Lisa-nee (Doujinshi)"
   },
   "contentRating": "pornographic",
   "score": 0.42759278,
   "languages": [
    "en"
   ]
  },
  {
   "id": "0d1dde7e-48c8-498e-944a-0934b9bfebc2",
   "title": {
    "en": "Azur Lane - Ai wa Ai yori Aoi? (Doujinshi)"
   },
   "contentRating": "pornographic",
   "score": 0.4233944,
   "languages": [
    "en"
   ]
  },
  {
   "id": "cfda91ef-d6ac-4056-b0dc-3a82d6bd6f6d",
   "title": {
    "en": "Otokonoko Natsu Hoshuu"
   },
   "contentRating": "pornographic",
   "score": 0.4101153,
   "languages": [
    "en"
   ]
  },
  {
   "id": "ac444580-6f9b-4972-b720-9c6e7f7e116a",
   "title": {
    "en": "BanG Dream! - dreaming bed (Doujinshi)"
   },
   "contentRating": "pornographic",
   "score": 0.40698668,
   "languages": [
    "en"
   ]
  },
  {
   "id": "89795b0c-f806-4b13-b48e-da2f37339240",
   "title": {
    "en": "Hitozuma Ane"
   },
   "contentRating": "pornographic",
   "score": 0.4040544,
   "languages": [
    "en",
    "it"
   ]
  },
  {
   "id": "67aa98c6-7fd6-4199-a82c-0ceb65112af0",
   "title": {
    "en": "Tiny Evil"
   },
   "contentRating": "pornographic",
   "score": 0.40146372,
   "languages": [
    "fr",
    "en"
   ]
  },
  {
   "id": "841c005b-43bb-474d-a61f-de447ba44752",
   "title": {
    "en": "VR no Megami-sama"
   },
   "contentRating": "pornographic",
   "score": 0.40065455,
   "languages": [
    "en"
   ]
  },
  {
   "id": "cea9a161-306c-4b22-90e5-a45f776aaf71",
   "title": {
    "en": "Azur Lane - Cute Girl. (Doujinshi)"
   },
   "contentRating": "pornographic",
   "score": 0.4003486,
   "languages": [
    "en"
   ]
  },
  {
   "id": "e3227025-563c-4610-9709-92a03733a4fe",
   "title": {
    "en": "Love Live! Sunshine!! - Bukkake H Coaster! (Doujinshi)"
   },
   "contentRating": "pornographic",
   "score": 0.39720312,
   "languages": [
    "en"
   ]
  },
  {
   "id": "830b9b56-2901-4776-8069-236ff6a341d4",
   "title": {
    "en": "BanG Dream! - How To Control Your Instincts (Doujinshi)"
   },
   "contentRating": "pornographic",
   "score": 0.39695984,
   "languages": [
    "en"
   ]
  },
  {
   "id": "cf3f26f5-28db-4c74-8288-4ea2a026bc9f",
   "title": {
    "en": "Amai no ga o Suki"
   },
   "contentRating": "pornographic",
   "score": 0.39643005,
   "languages": [
    "en"
   ]
  },
  {
   "id": "c48f83e7-124d-4f80-9fdc-ea9372e6b2ec",
   "title": {
    "en": "Love Live! Sunshine!! - A HAPPY LOVE LOVE LIFE! (Doujinshi)"
   },
   "contentRating": "pornographic",
   "score": 0.39597785,
   "languages": [
    "en"
   ]
  },
  {
   "id": "0b2a9c73-0e78-44b6-a4df-24cf7f4c00bb",
   "title": {
    "en": "BanG Dream! - 36.8°C no Maboroshi (Doujinshi)"
   },
   "contentRating": "pornographic",
   "score": 0.3954448,
   "languages": [
    "en"
   ]
  },
  {
   "id": "2fd8f36f-9b0d-4a20-a9d9-9a9e8ff5df9f",
   "title": {
    "en": "Gochuumon Wa Usagi Desu Ka - Saimin Nante Kakaru Wake Naijanaidesuka (Doujinshi)"
   },
   "contentRating": "pornographic",
   "score": 0.39387652,
   "languages": [
    "en"
   ]
  },
  {
   "id": "8f744fe4-a05c-47ea-8679-0c2f4035aac5",
   "title": {
    "en": "Girls' Frontline - Kalina's Sexual Desire"
   },
   "contentRating": "pornographic",
   "score": 0.3924026,
   "languages": [
    "en"
   ]
  },
  {
   "id": "bc2cd2ea-05e9-4467-9a5c-330ee4d70216",
   "title": {
    "en": "Josou no Pro ni Manabu Enkou no Susume"
   },
   "contentRating": "pornographic",
   "score": 0.39106986,
   "languages": [
    "en"
   ]
  }
 ],
 "updatedAt": "2023-11-03T08:09:33+00:00"
}