{
 "id": "9d6c46c4-7392-4329-bb96-ac5baf1f70e7",
 "title": {
  "en": "The Villainess Just Wants To Live In Peace!"
 },
 "contentRating": "safe",
 "matches": [
  {
   "id": "b00ca6fd-4fab-4c8f-a981-4a89cefc5d89",
   "title": {
    "en": "The Villainess Is Retiring"
   },
   "contentRating": "safe",
   "score": 0.4449592,
   "languages": [
    "es-la",
    "en",
    "id",
    "ru",
    "fa"
   ]
  },
  {
   "id": "bc20fa98-b707-43cc-b195-bcee8e518ed9",
   "title": {
    "en": "Rekishi ni Nokoru Akujo ni naru zo: Akuyaku Reijou ni naru hodo Ouji no Dekiai wa Kasoku suru you desu!"
   },
   "contentRating": "safe",
   "score": 0.434674,
   "languages": [
    "en",
    "id",
    "pt-br",
    "ru"
   ]
  },
  {
   "id": "50e0025c-8747-4edd-987d-baabf2caeb67",
   "title": {
    "en": "Isn't Being a Wicked Woman Much Better?"
   },
   "contentRating": "safe",
   "score": 0.41546768,
   "languages": [
    "en",
    "hr",
    "es-la",
    "pl"
   ]
  },
  {
   "id": "47c1cf74-e92d-43d1-806b-7ec08e6efe55",
   "title": {
    "en": "I'm a Villain, but I Saved the Female Lead"
   },
   "contentRating": "safe",
   "score": 0.41464946,
   "languages": [
    "en"
   ]
  },
  {
   "id": "2d668d5d-2e36-4362-b5ab-141215836368",
   "title": {
    "en": "Tired of Living in Fiction"
   },
   "contentRating": "safe",
   "score": 0.4078212,
   "languages": [
    "es-la",
    "pt-br",
    "en"
   ]
  },
  {
   "id": "e03ca79d-21eb-4342-a621-8ac7bf2a05b3",
   "title": {
    "en": "The Duke's Darling Daughter-in-Law"
   },
   "contentRating": "safe",
   "score": 0.390618,
   "languages": [
    "es-la",
    "en",
    "uk"
   ]
  },
  {
   "id": "dc84dffa-5ea9-4e62-b5f2-5a7a5fcc90ec",
   "title": {
    "en": "I Think I Have Transmigrated Somewhere"
   },
   "contentRating": "safe",
   "score": 0.38642582,
   "languages": [
    "en",
    "es-la",
    "pl"
   ]
  },
  {
   "id": "8848b6bd-dfae-4fec-8bc4-8a130394c9a1",
   "title": {
    "en": "The Precious Sister of the Villainous Grand Duke"
   },
   "contentRating": "safe",
   "score": 0.3834725,
   "languages": [
    "es-la",
    "fr",
    "ru",
    "en",
    "pl",
    "uk"
   ]
  },
  {
   "id": "aa4774a1-1ffc-4bc4-88f5-042a6d329f7b",
   "title": {
    "en": "Not Your Typical Reincarnation Story"
   },
   "contentRating": "safe",
   "score": 0.38015178,
   "languages": [
    "en",
    "pl"
   ]
  },
  {
   "id": "370243c4-a098-438d-b5a2-87316ae04ffb",
   "title": {
    "en": "The Archvillain's Daughter in Law"
   },
   "contentRating": "safe",
   "score": 0.37755746,
   "languages": [
    "en",
    "es-la"
   ]
  },
  {
   "id": "8cfc8b79-2c1b-4e33-beda-a0d70a7674ca",
   "title": {
    "en": "I Will Become the Villain's Poison Taster"
   },
   "contentRating": "safe",
   "score": 0.37522075,
   "languages": [
    "es-la",
    "en",
    "pl",
    "pt-br"
   ]
  },
  {
   "id": "3c3ec507-7177-4770-9e59-a70dbf81aaa9",
   "title": {
    "en": "Precious Daughter of the Greatest Martial Arts Villain"
   },
   "contentRating": "safe",
   "score": 0.37400907,
   "languages": [
    "es-la",
    "en"
   ]
  },
  {
   "id": "ee7b5c7e-a8eb-4c7a-93aa-17cae960acdf",
   "title": {
    "en": "‏I Will Fall With the Emperor"
   },
   "contentRating": "safe",
   "score": 0.37276444,
   "languages": [
    "en",
    "pt-br",
    "uk"
   ]
  },
  {
   "id": "d76a350d-c6b5-42bb-bfba-e521a3964a6a",
   "title": {
    "en": "The S-Class Lady"
   },
   "contentRating": "safe",
   "score": 0.36916047,
   "languages": [
    "es-la",
    "en",
    "pl",
    "pt-br"
   ]
  },
  {
   "id": "2b3ca0e3-4d7f-4f45-9b2e-ccfa51caddec",
   "title": {
    "en": "The Wicked Little Princess"
   },
   "contentRating": "safe",
   "score": 0.3680883,
   "languages": [
    "es-la",
    "en",
    "id",
    "pt-br"
   ]
  },
  {
   "id": "665a8030-e08f-4416-9059-292c1029b566",
   "title": {
    "en": "Looking for My One-Night Villainess"
   },
   "contentRating": "safe",
   "score": 0.36745405,
   "languages": [
    "en",
    "es-la"
   ]
  }
 ],
 "updatedAt": "2024-09-11T17:14:18+00:00"
}