{
 "id": "abb8bf44-358b-4fbc-9d98-8b7c9596636d",
 "title": {
  "en": "Pine Kiss"
 },
 "contentRating": "safe",
 "matches": [
  {
   "id": "25a776c9-5f92-4fdf-b78e-0607282ae5d7",
   "title": {
    "en": "Delicate ni Kiss Shite"
   },
   "contentRating": "safe",
   "score": 0.6183117
  },
  {
   "id": "b71d0862-c9fb-461c-b173-14104667e8fb",
   "title": {
    "en": "Aru Hi Bijin ni Nattara"
   },
   "contentRating": "safe",
   "score": 0.61718684
  },
  {
   "id": "2d77dc0f-749b-4167-a4ab-44e08b11dfdc",
   "title": {
    "en": "A House in Venice"
   },
   "contentRating": "safe",
   "score": 0.61492026
  },
  {
   "id": "36320572-a99d-4f8f-904e-630312cc963c",
   "title": {
    "en": "12 Months"
   },
   "contentRating": "safe",
   "score": 0.61393994
  },
  {
   "id": "1e76de7f-a81e-41e8-92fe-22596d29adbe",
   "title": {
    "en": "The Shaft of Light in the Blue"
   },
   "contentRating": "safe",
   "score": 0.6121341
  },
  {
   "id": "1eba1b31-9181-49b3-9cb5-a992f1236558",
   "title": {
    "en": "Why Do You Love Me?"
   },
   "contentRating": "safe",
   "score": 0.6102876
  },
  {
   "id": "82e08c3f-264f-484e-bee9-d85d2e29f6dc",
   "title": {
    "en": "Hatsukoi wa Yuki no You ni Awakute"
   },
   "contentRating": "safe",
   "score": 0.6099271
  },
  {
   "id": "21f71c14-ebb8-40bf-8e85-48b642d961fe",
   "title": {
    "en": "Sayonara Chocolate"
   },
   "contentRating": "safe",
   "score": 0.6088032
  },
  {
   "id": "845a5d9b-aded-4ba9-8ada-c4baefc3783f",
   "title": {
    "en": "Mou Hitori no Marionette"
   },
   "contentRating": "safe",
   "score": 0.6072048
  },
  {
   "id": "a23ddf40-8190-4bd1-9765-28053143f01a",
   "title": {
    "en": "37\u0026ordm;C no Boyfriend"
   },
   "contentRating": "safe",
   "score": 0.60717994
  },
  {
   "id": "729940e6-e49e-4ce0-9011-12c10b80f97e",
   "title": {
    "en": "Golden Japanesque"
   },
   "contentRating": "safe",
   "score": 0.606596
  },
  {
   "id": "f72b1592-248a-4d99-9007-ac46bd398ece",
   "title": {
    "en": "X2"
   },
   "contentRating": "safe",
   "score": 0.6063706
  },
  {
   "id": "40c1f19f-8bf4-490e-89f3-a894f5844a73",
   "title": {
    "en": "Ashita mo Kitto Koishiteru"
   },
   "contentRating": "safe",
   "score": 0.60618377
  },
  {
   "id": "dc0e12f9-f2b1-4c55-ad60-1f3f1bb54638",
   "title": {
    "en": "Ballad Made Soba ni Ite"
   },
   "contentRating": "safe",
   "score": 0.6061713
  },
  {
   "id": "f209e014-54e9-40f8-9f63-3906c85b5ab3",
   "title": {
    "en": "Kiss, Zekkou, Kiss"
   },
   "contentRating": "safe",
   "score": 0.60604775
  },
  {
   "id": "22d5a76e-de4d-4cf5-8508-d61e978ededa",
   "title": {
    "en": "Tokyo LACKs"
   },
   "contentRating": "safe",
   "score": 0.6060441
  },
  {
   "id": "2fb271d0-9c66-4cd9-8914-cb3119f95282",
   "title": {
    "en": "Togabito to Melody"
   },
   "contentRating": "safe",
   "score": 0.6058449
  },
  {
   "id": "d39d4f72-8b8d-4fd9-bf0e-19583667d592",
   "title": {
    "en": "Reds"
   },
   "contentRating": "safe",
   "score": 0.6057928
  },
  {
   "id": "9b7d94cb-d0aa-4c39-9fb9-490d793083b5",
   "title": {
    "en": "Nemurihime Age"
   },
   "contentRating": "safe",
   "score": 0.6054679
  },
  {
   "id": "71925d6b-c698-4e50-bb0e-21e68ba8fd88",
   "title": {
    "en": "Kakedashita Cupid"
   },
   "contentRating": "safe",
   "score": 0.60534763
  },
  {
   "id": "9b012c19-5b58-41f1-ab59-c46e6bf4b992",
   "title": {
    "en": "Night Lovers"
   },
   "contentRating": "safe",
   "score": 0.6051754
  },
  {
   "id": "df81e349-6c9c-4b0d-87e1-d20ea6fa03ca",
   "title": {
    "en": "Nemurihime ni Hyakumankai no Kiss"
   },
   "contentRating": "safe",
   "score": 0.604942
  },
  {
   "id": "ca7ad7c3-e7f7-4dae-82fe-9d10dad61345",
   "title": {
    "en": "Love Love - Kaporin no Yuuwaku Kiss 1"
   },
   "contentRating": "safe",
   "score": 0.6049131
  },
  {
   "id": "326526e2-7f05-43de-aff7-4264f0db5599",
   "title": {
    "en": "Samishii Hito"
   },
   "contentRating": "safe",
   "score": 0.6048541
  },
  {
   "id": "6c1e6f7a-3024-4971-a7be-24492c5a3207",
   "title": {
    "en": "Tsumasakidachi no Alice"
   },
   "contentRating": "safe",
   "score": 0.6048079
  }
 ],
 "updatedAt": "2021-05-13T00:57:47+00:00"
}