{
 "id": "c3e37161-3c45-4e81-89cc-7b2353617ca9",
 "title": {
  "en": "Isekai Goumon Hime"
 },
 "contentRating": "safe",
 "matches": [
  {
   "id": "1f07bed6-7431-4ea1-a69a-a0cd6bd7fceb",
   "title": {
    "en": "Memento Memori"
   },
   "contentRating": "safe",
   "score": 0.23201235,
   "languages": [
    "ru",
    "tr",
    "en"
   ]
  },
  {
   "id": "c6c428b5-b8e4-42f6-8777-8f548f45e79d",
   "title": {
    "en": "Isekai Meikyuu no Saishinbu o Mezasou"
   },
   "contentRating": "safe",
   "score": 0.22680561,
   "languages": [
    "ru",
    "en",
    "id",
    "es-la",
    "fr",
    "pt-br",
    "es"
   ]
  },
  {
   "id": "a1c58fbc-d805-4964-99fb-12b8fd07ec53",
   "title": {
    "en": "Hakui no Eiyuu"
   },
   "contentRating": "safe",
   "score": 0.20825897,
   "languages": [
    "en",
    "pt-br",
    "es-la",
    "ru"
   ]
  },
  {
   "id": "52925883-c86a-4f3c-a315-877a01258e14",
   "title": {
    "en": "Majo to Yajuu"
   },
   "contentRating": "safe",
   "score": 0.20785804,
   "languages": [
    "vi",
    "pt-br",
    "en",
    "ru"
   ]
  },
  {
   "id": "54202943-b55d-45a1-830f-44c9a8a691f0",
   "title": {
    "jp": "Sasaki to pii-chan, Isekai de Slow Life wo tanishimou to shitara, gendai de inou battle ni makikomareta ken ~ Mahou shoujo ga Up wo hajimeta you desu ~"
   },
   "contentRating": "safe",
   "score": 0.2061852,
   "languages": [
    "en",
    "es"
   ]
  },
  {
   "id": "7d7fee4a-41cf-4f9f-9d68-dc4bc4834016",
   "title": {
    "en": "Ghost Story Loop"
   },
   "contentRating": "safe",
   "score": 0.20038456,
   "languages": [
    "en",
    "id"
   ]
  },
  {
   "id": "6de510fb-cb39-45e9-8548-b211cdb0b771",
   "title": {
    "en": "Dantalian no Shoka"
   },
   "contentRating": "safe",
   "score": 0.20038456,
   "languages": [
    "es",
    "es-la",
    "en"
   ]
  },
  {
   "id": "bf791b79-9965-4b79-863e-2a02f01af252",
   "title": {
    "en": "Rewrite: SIDE-R"
   },
   "contentRating": "safe",
   "score": 0.19502261,
   "languages": [
    "en",
    "vi"
   ]
  },
  {
   "id": "5e9e50a7-39cc-447c-a5b3-a459bebd7f62",
   "title": {
    "en": "Human Chair"
   },
   "contentRating": "safe",
   "score": 0.19494623,
   "languages": [
    "en",
    "pl",
    "uk"
   ]
  },
  {
   "id": "41908d13-7ce6-4d64-8422-1740f9c6944c",
   "title": {
    "en": "Chloroform"
   },
   "contentRating": "safe",
   "score": 0.19383937,
   "languages": [
    "es-la",
    "en"
   ]
  },
  {
   "id": "1317eed1-130f-4bc6-b870-ae73d7e4c043",
   "title": {
    "en": "The Twin Empires"
   },
   "contentRating": "safe",
   "score": 0.19298692,
   "languages": [
    "es-la",
    "en"
   ]
  },
  {
   "id": "942c4d26-67a3-4a83-8a27-dbb68fe6ccad",
   "title": {
    "en": "Zero no Shiniki"
   },
   "contentRating": "safe",
   "score": 0.19298692,
   "languages": [
    "en",
    "fr"
   ]
  },
  {
   "id": "ada663c3-e8b7-4cce-a888-ebf6ea90721f",
   "title": {
    "en": "RDB"
   },
   "contentRating": "safe",
   "score": 0.19298692,
   "languages": [
    "ru",
    "en"
   ]
  },
  {
   "id": "75043a3f-daec-4ced-943c-65805e837c68",
   "title": {
    "en": "A Middle-aged Man Who Returned From Another World Becomes Unrivaled In The Apocalyptic World"
   },
   "contentRating": "safe",
   "score": 0.19238904,
   "languages": [
    "en",
    "pt-br"
   ]
  },
  {
   "id": "ffdbc599-2857-4ada-acee-cd95fe417a6b",
   "title": {
    "en": "Goumontou wa Nemuranai - Doukeshi no Shou"
   },
   "contentRating": "safe",
   "score": 0.18981035,
   "languages": [
    "en"
   ]
  },
  {
   "id": "8bcdbfe3-3424-4978-a48d-17d1b968ddd7",
   "title": {
    "en": "Yaritsukai to, Kuroneko"
   },
   "contentRating": "safe",
   "score": 0.18881969,
   "languages": [
    "en"
   ]
  }
 ],
 "updatedAt": "2023-11-20T18:57:24+00:00"
}