{
 "id": "d9a44ef7-91a3-43a2-a1f1-ec0fb296c3c0",
 "title": {
  "en": "I Have Something to Tell You"
 },
 "contentRating": "safe",
 "matches": [
  {
   "id": "960c5e23-d0f7-4eac-870a-295cbc6157dc",
   "title": {
    "en": "From Nightmare to Love"
   },
   "contentRating": "safe",
   "score": 0.42560488
  },
  {
   "id": "2007e813-0af9-47d8-b040-d857b46972a0",
   "title": {
    "en": "Hana wa Knife wo Mi ni Matou"
   },
   "contentRating": "safe",
   "score": 0.42197198
  },
  {
   "id": "5f85a246-16b8-43c9-80b2-2f0a73cae66e",
   "title": {
    "en": "from End"
   },
   "contentRating": "safe",
   "score": 0.41726798
  },
  {
   "id": "f9d5d573-8514-49c7-8689-9c7b8805adba",
   "title": {
    "en": "Taiyou ga Miteiru (Kamoshirenai Kara)"
   },
   "contentRating": "safe",
   "score": 0.40444034
  },
  {
   "id": "6922fc4a-3e79-4c95-b860-b8a1b09588fe",
   "title": {
    "en": "Pink to Gray"
   },
   "contentRating": "safe",
   "score": 0.39914498
  },
  {
   "id": "30a36e4a-b92b-4701-9ed9-c5e32d4312bb",
   "title": {
    "en": "Haikyo Shoujo"
   },
   "contentRating": "safe",
   "score": 0.3891423
  },
  {
   "id": "9d2fc75b-8803-4b0d-8550-3c13a6a40688",
   "title": {
    "en": "Gunjou - Ai ga Shizunda Umi no Iro"
   },
   "contentRating": "safe",
   "score": 0.3891423
  },
  {
   "id": "23f1d1b1-5828-472d-964d-6e55c528f74b",
   "title": {
    "en": "Yume Kurai"
   },
   "contentRating": "safe",
   "score": 0.3891423
  },
  {
   "id": "b7bd879c-3f00-4968-8309-146a6d23dd08",
   "title": {
    "en": "Knife"
   },
   "contentRating": "safe",
   "score": 0.3891423
  },
  {
   "id": "2a27a1bd-c22c-4ec9-8110-2573484ace2b",
   "title": {
    "en": "Ageha"
   },
   "contentRating": "safe",
   "score": 0.3891423
  }
 ],
 "updatedAt": "2021-05-09T22:10:39+00:00"
}