{
 "id": "4a4d2e5f-c4f4-47e3-9725-133bd5869c05",
 "type": "manga",
 "attributes": {
  "title": {
   "en": "Rabukome Manga ni Haitte Shimatta no de, Oshi no Make Heroine wo Zenryoku de Shiawase ni suru"
  },
  "altTitles": [
   {
    "ja": "ラブコメ漫画に入ってしまったので、推しの負けヒロインを全力で幸せにする"
   },
   {
    "zh-hk": "穿越進戀愛喜劇漫畫, 這次一定要讓我推的敗犬幸福"
   },
   {
    "id": "Karena aku sudah masuk ke kedalam dunia manga romcom, aku akan melakukan yang terbaik untuk membuat Heroine yang kalah dapat bahagia."
   },
   {
    "en": "Since I’ve Entered the World of Romantic Comedy Manga, I’ll Do My Best to Make the Losing Heroine Happy"
   }
  ],
  "description": {
   "en": "In the world of a popular rom-com manga, my only mission as the friend of the MC is to make the losing heroine, Sei-chan, happy!\n\n\"I'll definitely make you happy. Please go out with me.\"\n\n\"W-Wait, what!? Y-You're being serious...!?\"\n\nThe manga adaptation of the sweet rom-com from Kakuyomu starts now!",
   "id": "Seorang anak sma otaku mempunyai waifu yang kalah war, setelah pulang kerja part time ia pun membeli kebutuhan otakunya lalu dia di tabrak oleh truck-kun yang supirnya lagi turu dan malah reinkarnasi kedalam manga kesukaannya namun setelah sampai disana dia malah nembak waifunya sendiri!!?",
   "vi": "Tôi rất thích một bộ manga romcom.\n\nTuy nhiên, nhân vật mà tôi thích lại là một nữ phụ, một nhân vật không bao giờ có thể đến được với... nam chính.\n\nMột ngày nọ, tôi bị tông bởi một chiếc xe tải và khi tỉnh dậy thì nhận ra mình đang vào vai người bạn thân của nam chính trong bộ manga romcom đó.\n\nNhư vậy, vai trò của tôi lúc này chỉ có một\n\n\"Tớ thích cậu, chắc chắn tớ sẽ khiến cho cậu hạnh phúc, Sei-chan!\"\n\nChắc chắn, tôi sẽ thay đổi câu chuyện tình buồn của nữ phụ, và khiến cho cô ấy hạnh phúc!"
  },
  "links": {
   "al": "154877",
   "amz": "https://www.amazon.co.jp/dp/B0CK21FJ26",
   "ap": "love-comedy-manga-ni-haitteshimatta-node-oshi-no-make-heroine-wo-zenryoku-de-shiawase-ni-suru",
   "bw": "series/438542",
   "cdj": "https://www.cdjapan.co.jp/product/NEOBK-2907312",
   "kt": "love-come-manga-ni-haitte-shimatta-node-oshi-no-make-heroine-wo-zenryoku-de-shiawase-ni-suru",
   "mal": "152087",
   "mu": "2nwymbv",
   "nu": "since-ive-entered-the-world-of-romantic-comedy-manga-ill-do-my-best-to-make-the-heroine-who-doesnt-stick-with-the-hero-happy",
   "raw": "https://comic.webnewtype.com/contents/lovecome/"
  },
  "originalLanguage": "ja",
  "status": "hiatus",
  "year": 2022,
  "contentRating": "safe",
  "availableTranslatedLanguages": [
   "en",
   "id",
   "uk",
   "es-la",
   "vi",
   "pt-br"
  ],
  "latestUploadedChapter": "d435580d-6685-46ee-932c-947bf3342754",
  "tags": [
   {
    "id": "0bc90acb-ccc1-44ca-a34a-b9f3a73259d0",
    "type": "tag",
    "attributes": {
     "name": {
      "en": "Reincarnation"
     },
     "description": {},
     "group": "theme",
     "version": 1
    }
   },
   {
    "id": "423e2eae-a7a2-4a8b-ac03-a8351462d71d",
    "type": "tag",
    "attributes": {
     "name": {
      "en": "Romance"
     },
     "description": {},
     "group": "genre",
     "version": 1
    }
   },
   {
    "id": "4d32cc48-9f00-4cca-9b5a-a839f0764984",
    "type": "tag",
    "attributes": {
     "name": {
      "en": "Comedy"
     },
     "description": {},
     "group": "genre",
     "version": 1
    }
   },
   {
    "id": "ace04997-f6bd-436e-b261-779182193d3d",
    "type": "tag",
    "attributes": {
     "name": {
      "en": "Isekai"
     },
     "description": {},
     "group": "genre",
     "version": 1
    }
   },
   {
    "id": "caaa44eb-cd40-4177-b930-79d3ef2afe87",
    "type": "tag",
    "attributes": {
     "name": {
      "en": "School Life"
     },
     "description": {},
     "group": "theme",
     "version": 1
    }
   },
   {
    "id": "f4122d1c-3b44-44d0-9936-ff7502c39ad3",
    "type": "tag",
    "attributes": {
     "name": {
      "en": "Adaptation"
     },
     "description": {},
     "group": "format",
     "version": 1
    }
   }
  ],
  "state": "published",
  "version": 31,
  "createdAt": "2022-09-20T12:33:45+00:00",
  "updatedAt": "2023-12-10T18:11:50+00:00"
 },
 "relationships": [
  {
   "id": "cd6dab85-13f9-4c06-9b9a-faa86064b6e6",
   "type": "author",
   "attributes": {
    "biography": {},
    "booth": null,
    "createdAt": "2021-04-19T21:59:45+00:00",
    "fanBox": null,
    "fantia": null,
    "imageUrl": null,
    "melonBook": null,
    "name": "Shiryu",
    "naver": null,
    "nicoVideo": null,
    "pixiv": null,
    "skeb": null,
    "tumblr": null,
    "twitter": "https://twitter.com/nissyhiro222",
    "updatedAt": "2023-08-08T02:58:26+00:00",
    "version": 2,
    "website": "https://www.ranobeshiryu.com",
    "weibo": null,
    "youtube": null
   }
  },
  {
   "id": "ab86ccea-2899-41ff-bd0f-aefaf7e7a31c",
   "type": "artist",
   "attributes": {
    "biography": {},
    "booth": null,
    "createdAt": "2022-09-20T12:26:02+00:00",
    "fanBox": null,
    "fantia": null,
    "imageUrl": null,
    "melonBook": null,
    "name": "Bara",
    "naver": null,
    "nicoVideo": null,
    "pixiv": "https://www.pixiv.net/users/13765263",
    "skeb": null,
    "tumblr": null,
    "twitter": "https://twitter.com/03_Bara_",
    "updatedAt": "2023-08-08T03:02:49+00:00",
    "version": 2,
    "website": null,
    "weibo": null,
    "youtube": null
   }
  },
  {
   "id": "cdfbd2b8-aa6c-4727-ac29-846e2c011bba",
   "type": "artist",
   "attributes": {
    "biography": {},
    "booth": null,
    "createdAt": "2021-04-19T21:59:45+00:00",
    "fanBox": null,
    "fantia": null,
    "imageUrl": null,
    "melonBook": null,
    "name": "Shiharu",
    "naver": null,
    "nicoVideo": null,
    "pixiv": "https://www.pixiv.net/en/users/598708",
    "skeb": null,
    "tumblr": null,
    "twitter": "https://twitter.com/siharu4s",
    "updatedAt": "2023-07-29T16:30:16+00:00",
    "version": 2,
    "website": null,
    "weibo": null,
    "youtube": null
   }
  },
  {
   "id": "011e7549-0e91-4700-a84f-50a24b761c39",
   "type": "cover_art",
   "attributes": {
    "createdAt": "2023-10-06T23:56:52+00:00",
    "description": "Volume Cover From BookWalker",
    "fileName": "a73ffd15-dd18-4ba7-a365-8e67e17d5c25.jpg",
    "locale": "ja",
    "updatedAt": "2023-10-06T23:56:52+00:00",
    "version": 1,
    "volume": "1"
   }
  },
  {
   "id": "996939eb-e208-4a6d-ac5a-d09cdb484b3a",
   "type": "creator"
  }
 ]
}