{
 "id": "759c4bbc-d953-41e0-8113-41ab58b8b7d6",
 "type": "manga",
 "attributes": {
  "title": {
   "en": "Honzuki no Gekokujou ~Shisho ni Naru Tame ni wa Shudan wo Erandeiraremasen~ Drama CD3"
  },
  "altTitles": [
   {
    "ja": "本好きの下剋上～司書になるためには手段を選んでいられません～ドラマCD3"
   },
   {
    "en": "Ascendance of a Bookworm ~I'll do anything to become a librarian~ Drama CD3"
   }
  ],
  "description": {},
  "links": {
   "raw": "http://www.tobooks.jp/booklove_dramacd3/contents_04.html"
  },
  "originalLanguage": "ja",
  "lastChapter": "1",
  "publicationDemographic": "shoujo",
  "status": "completed",
  "year": 2019,
  "contentRating": "safe",
  "availableTranslatedLanguages": [
   "en"
  ],
  "latestUploadedChapter": "30282c98-c0d8-47f4-bd3f-34e4aff24256",
  "tags": [
   {
    "id": "4d32cc48-9f00-4cca-9b5a-a839f0764984",
    "type": "tag",
    "attributes": {
     "name": {
      "en": "Comedy"
     },
     "description": {},
     "group": "genre",
     "version": 1
    }
   },
   {
    "id": "ace04997-f6bd-436e-b261-779182193d3d",
    "type": "tag",
    "attributes": {
     "name": {
      "en": "Isekai"
     },
     "description": {},
     "group": "genre",
     "version": 1
    }
   },
   {
    "id": "b9af3a63-f058-46de-a9a0-e0c13906197a",
    "type": "tag",
    "attributes": {
     "name": {
      "en": "Drama"
     },
     "description": {},
     "group": "genre",
     "version": 1
    }
   },
   {
    "id": "cdc58593-87dd-415e-bbc0-2ec27bf404cc",
    "type": "tag",
    "attributes": {
     "name": {
      "en": "Fantasy"
     },
     "description": {},
     "group": "genre",
     "version": 1
    }
   },
   {
    "id": "e5301a23-ebd9-49dd-a0cb-2add944c7fe9",
    "type": "tag",
    "attributes": {
     "name": {
      "en": "Slice of Life"
     },
     "description": {},
     "group": "genre",
     "version": 1
    }
   }
  ],
  "state": "published",
  "version": 4,
  "createdAt": "2023-01-30T05:28:09+00:00",
  "updatedAt": "2023-01-30T07:04:14+00:00"
 },
 "relationships": [
  {
   "id": "27569e2d-2b27-44c4-9ee6-4d25449c7b17",
   "type": "author",
   "attributes": {
    "biography": {
     "en": "**Name In Native Language:** 香月美夜\n\nKazuki began crafting novels during her second year of junior high. After successfully navigating an entrance exam, she entered a national university. However, the demands of work interrupted her writing pursuits. It wasn't until she married and her child started kindergarten that Kazuki found herself with more free time, allowing her to rekindle her passion for writing. In 2013, she commenced publishing her novel \"Ascendance of a Bookworm\" on the user-generated platform Shōsetsuka ni Narō, achieving notable success. By 2015, she officially debuted with the same series under the T.O. Books imprint.\n\nFrom 2015 to 2017, she wrote a series of essays for \"Everyone's Library\" (みんなの図書館, Minna no Toshokan), a journal released by The Society of Study on Library Problems. \n\nSupport the Author:\n[Ascendance of a Bookworm: Light Novel](https://j-novel.club/series/ascendance-of-a-bookworm)\n[Ascendance of a Bookworm: Manga](https://j-novel.club/series/ascendance-of-a-bookworm-manga)\n[Ascendance of a Bookworm: Fanbook](https://j-novel.club/series/ascendance-of-a-bookworm-fanbook)\n[Ascendance of a Bookworm: Short Story Collection](https://j-novel.club/series/ascendance-of-a-bookworm-short-story-collection)\n[Ascendance of a Bookworm: Royal Academy Stories - First Year](https://j-novel.club/series/ascendance-of-a-bookworm-royal-academy-stories-first-year)\n\n\n"
    },
    "booth": null,
    "createdAt": "2021-04-19T21:59:45+00:00",
    "fanBox": null,
    "fantia": null,
    "imageUrl": null,
    "melonBook": null,
    "name": "Kazuki Miya",
    "namicomi": null,
    "naver": null,
    "nicoVideo": null,
    "pixiv": null,
    "skeb": null,
    "tumblr": null,
    "twitter": "https://twitter.com/miyakazuki01",
    "updatedAt": "2024-08-10T11:09:00+00:00",
    "version": 8,
    "website": "https://mypage.syosetu.com/372556/",
    "weibo": null,
    "youtube": null
   }
  },
  {
   "id": "7519fb6c-1c68-4709-95fb-89782592ed21",
   "type": "artist",
   "attributes": {
    "biography": {
     "en": "**Name In Native Language:** 鈴華\n\n**Circle:** Rekkyo. (列挙。)"
    },
    "booth": null,
    "createdAt": "2021-04-19T21:59:45+00:00",
    "fanBox": "https://suzupaca.fanbox.cc/",
    "fantia": null,
    "imageUrl": null,
    "melonBook": null,
    "name": "Suzuka",
    "namicomi": null,
    "naver": null,
    "nicoVideo": null,
    "pixiv": "https://www.pixiv.net/users/517836",
    "skeb": null,
    "tumblr": null,
    "twitter": "https://twitter.com/suzupaca",
    "updatedAt": "2024-08-10T11:10:01+00:00",
    "version": 3,
    "website": "http://suzuka228086.web.fc2.com/",
    "weibo": null,
    "youtube": null
   }
  },
  {
   "id": "1508a93f-c583-4772-a27a-681d8391fc38",
   "type": "cover_art",
   "attributes": {
    "createdAt": "2023-01-30T05:31:04+00:00",
    "description": "",
    "fileName": "e6cc3107-6d44-4e7d-8d3e-3081070365fd.png",
    "locale": "ja",
    "updatedAt": "2023-06-26T03:43:58+00:00",
    "version": 2,
    "volume": "1"
   }
  },
  {
   "id": "3017d3e0-bf34-4772-b752-bcc93b763ff9",
   "type": "manga",
   "related": "same_franchise"
  },
  {
   "id": "316d3d09-bb83-49da-9d90-11dc7ce40967",
   "type": "manga",
   "related": "adapted_from"
  },
  {
   "id": "85ce7857-3d01-4b0a-adff-7a4cba347ced",
   "type": "manga",
   "related": "adapted_from"
  },
  {
   "id": "c0ad8919-4646-4a61-adf9-0fd6d8612efa",
   "type": "manga",
   "related": "adapted_from"
  },
  {
   "id": "f1311d54-99bc-49ed-b12f-099b9a40c104",
   "type": "manga",
   "related": "adapted_from"
  },
  {
   "id": "9f5c09c9-e232-4f04-9baa-833d38286c17",
   "type": "creator"
  }
 ]
}