{
 "id": "871a507e-5dec-4693-9fb3-032a0301ed91",
 "type": "manga",
 "attributes": {
  "title": {
   "en": "Oshikake Ouji wa Nido Oishii"
  },
  "altTitles": [
   {
    "ja": "おしかけ王子は２度おいしい"
   },
   {
    "en": "Double the Trouble, Twice as Nice"
   }
  ],
  "description": {
   "en": "A bottom corporate slave gets some heart and physical healing from the high-spec boy she picked up...? After staying up all night from doing overtime, Yuri Hayama was dumped by her boyfriend just when she thought they would get married. On the way home, she helped a little boy and the next day, she woke up hearing \"Good morning\" from a handsome guy? This is a story about a forcible love with a mysterious younger boy!"
  },
  "links": {
   "al": "136966",
   "engtl": "https://comikey.com/comics/double-the-trouble-twice-as-nice-manga/424/",
   "mu": "dt30wl9"
  },
  "originalLanguage": "ja",
  "publicationDemographic": "josei",
  "status": "ongoing",
  "year": 2021,
  "contentRating": "safe",
  "availableTranslatedLanguages": [
   "en"
  ],
  "latestUploadedChapter": "5714b296-bb75-429a-8119-f2c9d2687ca7",
  "tags": [
   {
    "id": "256c8bd9-4904-4360-bf4f-508a76d67183",
    "type": "tag",
    "attributes": {
     "name": {
      "en": "Sci-Fi"
     },
     "description": {},
     "group": "genre",
     "version": 1
    }
   },
   {
    "id": "423e2eae-a7a2-4a8b-ac03-a8351462d71d",
    "type": "tag",
    "attributes": {
     "name": {
      "en": "Romance"
     },
     "description": {},
     "group": "genre",
     "version": 1
    }
   },
   {
    "id": "4d32cc48-9f00-4cca-9b5a-a839f0764984",
    "type": "tag",
    "attributes": {
     "name": {
      "en": "Comedy"
     },
     "description": {},
     "group": "genre",
     "version": 1
    }
   }
  ],
  "state": "published",
  "version": 10,
  "createdAt": "2021-12-01T21:57:17+00:00",
  "updatedAt": "2022-12-03T22:21:30+00:00"
 },
 "relationships": [
  {
   "id": "20c44eba-a9a6-4e32-abcf-7b732ecf9706",
   "type": "author",
   "attributes": {
    "biography": {},
    "booth": null,
    "createdAt": "2021-12-01T21:54:51+00:00",
    "fanBox": null,
    "fantia": null,
    "imageUrl": null,
    "melonBook": null,
    "name": "Ichino Ryou",
    "naver": null,
    "nicoVideo": null,
    "pixiv": null,
    "skeb": null,
    "tumblr": null,
    "twitter": null,
    "updatedAt": "2021-12-01T21:54:51+00:00",
    "version": 1,
    "website": null,
    "weibo": null,
    "youtube": null
   }
  },
  {
   "id": "20c44eba-a9a6-4e32-abcf-7b732ecf9706",
   "type": "artist",
   "attributes": {
    "biography": {},
    "booth": null,
    "createdAt": "2021-12-01T21:54:51+00:00",
    "fanBox": null,
    "fantia": null,
    "imageUrl": null,
    "melonBook": null,
    "name": "Ichino Ryou",
    "naver": null,
    "nicoVideo": null,
    "pixiv": null,
    "skeb": null,
    "tumblr": null,
    "twitter": null,
    "updatedAt": "2021-12-01T21:54:51+00:00",
    "version": 1,
    "website": null,
    "weibo": null,
    "youtube": null
   }
  },
  {
   "id": "b9af424f-0a33-4526-b484-d49e08bf250a",
   "type": "cover_art",
   "attributes": {
    "createdAt": "2021-12-01T21:57:23+00:00",
    "description": "",
    "fileName": "a8071fb1-d3f9-47fb-9a15-0c2a4b69ea0d.jpg",
    "locale": "ja",
    "updatedAt": "2021-12-01T21:57:23+00:00",
    "version": 1,
    "volume": "1"
   }
  }
 ]
}