{
 "id": "b93e91ea-bdb6-437c-8ea6-32662a56dfc6",
 "type": "manga",
 "attributes": {
  "title": {
   "en": "Best Served Cold"
  },
  "altTitles": [
   {
    "zh": "從報復開始"
   },
   {
    "ko": "쓰레기를위하여"
   }
  ],
  "description": {
   "en": "Minjoo’s lonely. She keeps herself busy with social media, but that doesn’t help the fact that her husband’s distant and she’s virtually friendless. Nothing changes until she runs into Seo Jia, a handsome girl who’s just moved in downstairs. Minjoo’s never met anyone like Jia before, and can’t help but fall for Jia’s charms. But little does Minjoo know that their meeting wasn’t exactly serendipitious; in fact, every one of Jia's moves is carefully calculated...so that she can get her revenge!"
  },
  "links": {
   "ap": "best-served-cold",
   "engtl": "https://www.lezhinus.com/en/comic/served_cold",
   "mu": "m9fdwek"
  },
  "originalLanguage": "ko",
  "lastChapter": "77",
  "status": "completed",
  "year": 2021,
  "contentRating": "erotica",
  "tags": [
   {
    "id": "3e2b8dae-350e-4ab8-a8ce-016e844b9f0d",
    "type": "tag",
    "attributes": {
     "name": {
      "en": "Long Strip"
     },
     "description": {},
     "group": "format",
     "version": 1
    }
   },
   {
    "id": "423e2eae-a7a2-4a8b-ac03-a8351462d71d",
    "type": "tag",
    "attributes": {
     "name": {
      "en": "Romance"
     },
     "description": {},
     "group": "genre",
     "version": 1
    }
   },
   {
    "id": "a3c67850-4684-404e-9b7f-c69850ee5da6",
    "type": "tag",
    "attributes": {
     "name": {
      "en": "Girls' Love"
     },
     "description": {},
     "group": "genre",
     "version": 1
    }
   },
   {
    "id": "b9af3a63-f058-46de-a9a0-e0c13906197a",
    "type": "tag",
    "attributes": {
     "name": {
      "en": "Drama"
     },
     "description": {},
     "group": "genre",
     "version": 1
    }
   },
   {
    "id": "e197df38-d0e7-43b5-9b09-2842d0c326dd",
    "type": "tag",
    "attributes": {
     "name": {
      "en": "Web Comic"
     },
     "description": {},
     "group": "format",
     "version": 1
    }
   },
   {
    "id": "f5ba408b-0e7a-484d-8d49-4e9125ac96de",
    "type": "tag",
    "attributes": {
     "name": {
      "en": "Full Color"
     },
     "description": {},
     "group": "format",
     "version": 1
    }
   }
  ],
  "state": "published",
  "version": 3,
  "createdAt": "2024-05-03T17:33:52+00:00",
  "updatedAt": "2024-05-03T21:40:30+00:00"
 },
 "relationships": [
  {
   "id": "622cc54e-e432-41fb-a75e-998f57d6314b",
   "type": "author",
   "attributes": {
    "biography": {},
    "booth": null,
    "createdAt": "2021-12-20T20:51:17+00:00",
    "fanBox": null,
    "fantia": null,
    "imageUrl": null,
    "melonBook": null,
    "name": "Jong-Geon Kim",
    "namicomi": null,
    "naver": null,
    "nicoVideo": null,
    "pixiv": null,
    "skeb": null,
    "tumblr": null,
    "twitter": null,
    "updatedAt": "2021-12-20T20:51:17+00:00",
    "version": 1,
    "website": null,
    "weibo": null,
    "youtube": null
   }
  },
  {
   "id": "70881055-6da0-45a0-8650-99ed40499a84",
   "type": "author",
   "attributes": {
    "biography": {},
    "booth": null,
    "createdAt": "2021-12-21T05:09:45+00:00",
    "fanBox": null,
    "fantia": null,
    "imageUrl": null,
    "melonBook": null,
    "name": "Kim Jong Geon (김종건)",
    "namicomi": null,
    "naver": null,
    "nicoVideo": null,
    "pixiv": null,
    "skeb": null,
    "tumblr": null,
    "twitter": "https://twitter.com/AGALSSAMUL",
    "updatedAt": "2022-05-07T01:07:09+00:00",
    "version": 3,
    "website": "https://dotae.postype.com/",
    "weibo": null,
    "youtube": null
   }
  },
  {
   "id": "622cc54e-e432-41fb-a75e-998f57d6314b",
   "type": "artist",
   "attributes": {
    "biography": {},
    "booth": null,
    "createdAt": "2021-12-20T20:51:17+00:00",
    "fanBox": null,
    "fantia": null,
    "imageUrl": null,
    "melonBook": null,
    "name": "Jong-Geon Kim",
    "namicomi": null,
    "naver": null,
    "nicoVideo": null,
    "pixiv": null,
    "skeb": null,
    "tumblr": null,
    "twitter": null,
    "updatedAt": "2021-12-20T20:51:17+00:00",
    "version": 1,
    "website": null,
    "weibo": null,
    "youtube": null
   }
  },
  {
   "id": "70881055-6da0-45a0-8650-99ed40499a84",
   "type": "artist",
   "attributes": {
    "biography": {},
    "booth": null,
    "createdAt": "2021-12-21T05:09:45+00:00",
    "fanBox": null,
    "fantia": null,
    "imageUrl": null,
    "melonBook": null,
    "name": "Kim Jong Geon (김종건)",
    "namicomi": null,
    "naver": null,
    "nicoVideo": null,
    "pixiv": null,
    "skeb": null,
    "tumblr": null,
    "twitter": "https://twitter.com/AGALSSAMUL",
    "updatedAt": "2022-05-07T01:07:09+00:00",
    "version": 3,
    "website": "https://dotae.postype.com/",
    "weibo": null,
    "youtube": null
   }
  },
  {
   "id": "ad02c7f3-8b8b-4011-8d36-2c90021572ca",
   "type": "cover_art",
   "attributes": {
    "createdAt": "2024-05-03T17:37:23+00:00",
    "description": "",
    "fileName": "04d8191f-2cf1-43ab-97b8-49db0f8515a8.jpg",
    "locale": "ko",
    "updatedAt": "2024-05-03T17:37:23+00:00",
    "version": 1,
    "volume": "1"
   }
  },
  {
   "id": "7829115d-9a56-4e8f-a1f1-77b3cc144c26",
   "type": "creator"
  }
 ]
}