{
 "id": "c1c4dcbe-e262-4805-9fd0-90915ce7b681",
 "type": "manga",
 "attributes": {
  "title": {
   "en": "Vampire Girl Karen"
  },
  "altTitles": [
   {
    "ja-ro": "Kyuuketsu Shoujo Karen"
   },
   {
    "ja": "吸血少女カレン"
   }
  ],
  "description": {
   "en": "A story of blood and tears about Karen, an unfortunate girl who becomes a vampire."
  },
  "links": {
   "amz": "https://www.amazon.co.jp/吸血少女カレン-ゴマブックス×ナンバーナイン-浜慎二-ebook/dp/B09TPKLP9T",
   "bw": "de60535d89-d6ff-4eed-aca4-c3221677ed78",
   "ebj": "https://ebookjapan.yahoo.co.jp/books/686562/",
   "mu": "lkq5j9r"
  },
  "originalLanguage": "ja",
  "lastVolume": "1",
  "lastChapter": "11",
  "publicationDemographic": "shoujo",
  "status": "completed",
  "year": 1975,
  "contentRating": "safe",
  "tags": [
   {
    "id": "cdad7e68-1419-41dd-bdce-27753074a640",
    "type": "tag",
    "attributes": {
     "name": {
      "en": "Horror"
     },
     "description": {},
     "group": "genre",
     "version": 1
    }
   },
   {
    "id": "d7d1730f-6eb0-4ba6-9437-602cac38664c",
    "type": "tag",
    "attributes": {
     "name": {
      "en": "Vampires"
     },
     "description": {},
     "group": "theme",
     "version": 1
    }
   }
  ],
  "state": "published",
  "version": 2,
  "createdAt": "2024-01-06T23:49:28+00:00",
  "updatedAt": "2024-01-06T23:49:40+00:00"
 },
 "relationships": [
  {
   "id": "2cda876f-3a21-44fd-860e-5b4889b36923",
   "type": "author",
   "attributes": {
    "biography": {},
    "booth": null,
    "createdAt": "2024-01-06T10:35:19+00:00",
    "fanBox": null,
    "fantia": null,
    "imageUrl": null,
    "melonBook": null,
    "name": "Hama Shinji",
    "namicomi": null,
    "naver": null,
    "nicoVideo": null,
    "pixiv": null,
    "skeb": null,
    "tumblr": null,
    "twitter": null,
    "updatedAt": "2024-01-06T10:35:19+00:00",
    "version": 1,
    "website": null,
    "weibo": null,
    "youtube": null
   }
  },
  {
   "id": "2cda876f-3a21-44fd-860e-5b4889b36923",
   "type": "artist",
   "attributes": {
    "biography": {},
    "booth": null,
    "createdAt": "2024-01-06T10:35:19+00:00",
    "fanBox": null,
    "fantia": null,
    "imageUrl": null,
    "melonBook": null,
    "name": "Hama Shinji",
    "namicomi": null,
    "naver": null,
    "nicoVideo": null,
    "pixiv": null,
    "skeb": null,
    "tumblr": null,
    "twitter": null,
    "updatedAt": "2024-01-06T10:35:19+00:00",
    "version": 1,
    "website": null,
    "weibo": null,
    "youtube": null
   }
  },
  {
   "id": "42dd7d19-3b6e-4b08-9cf5-27ae1938bbea",
   "type": "cover_art",
   "attributes": {
    "createdAt": "2024-01-06T23:49:32+00:00",
    "description": "",
    "fileName": "8b546cab-4204-4635-bc05-b6bb758d3bd7.png",
    "locale": "ja",
    "updatedAt": "2024-01-06T23:49:32+00:00",
    "version": 1,
    "volume": "1"
   }
  },
  {
   "id": "ecf379e6-bc34-42c4-b25d-63698875cdfb",
   "type": "creator"
  }
 ]
}